inception_helper_func/__init__.py
inception_helper_func/collaboration.py
inception_helper_func/common_validator.py
inception_helper_func/default.py
inception_helper_func/format.py
inception_helper_func/id.py
inception_helper_func/money.py
inception_helper_func/operation.py
inception_helper_func/s3service.py
inception_helper_func/sort_query.py
inception_helper_func-0.4.8.dist-info/LICENSE
inception_helper_func-0.4.8.dist-info/METADATA
inception_helper_func-0.4.8.dist-info/WHEEL
inception_helper_func-0.4.8.dist-info/top_level.txt
inception_helper_func-0.4.8.dist-info/RECORD
