Metadata-Version: 2.1
Name: inception_helper_func
Version: 0.4.8
Summary: inception_helper_func is a package that contains helper functions for the InceptionForce project
Home-page: https://github.com/KhaduaBloom/inceptionforcepackages/tree/main/PythonPackage/inceptionHelperFunc
Author: KhaduaBloom
Author-email: khaduabloom@gmail.com
Classifier: Programming Language :: Python :: 3
Classifier: License :: OSI Approved :: MIT License
Classifier: Operating System :: OS Independent
Requires-Python: >=3.13.0
License-File: LICENSE
Requires-Dist: graypy==2.1.0
Requires-Dist: psutil==6.1.0
Requires-Dist: pytz==2025.2
Requires-Dist: fastapi
Requires-Dist: pydantic-settings
Requires-Dist: aiohttp[speedups]
Requires-Dist: sqlalchemy
Requires-Dist: pymongo[srv]
Requires-Dist: elasticsearch==8.17.2
Requires-Dist: opensearch-py
Requires-Dist: requests-aws4auth
Requires-Dist: boto3
